<?xml version="1.0"?>
<mads:mads xmlns:xlink="http://www.w3.org/1999/xlink" xmlns:mods="http://www.loc.gov/mods/v3"
  xmlns:mads="http://www.loc.gov/mads/v2" xmlns:xsi="http://www.w3.org/2001/XMLSchema-instance"
  version="2.0"
  xsi:schemaLocation="http://www.loc.gov/mads/ http://www.loc.gov/standards/mads/mads.xsd http://www.loc.gov/mods/v3 http://www.loc.gov/standards/mods/v3/mods-3-2.xsd">
  <mads:authority>
    <mads:name type="personal" authority="viaf" authorityURI="https://viaf.org/viaf/"
      valueURI="https://viaf.org/viaf/29920439/">
      <mads:namePart>Callicrates</mads:namePart>
      <mads:namePart type="termsOfAddress">Comicus</mads:namePart>
      <mads:namePart type="date">Person der Antike</mads:namePart>
    </mads:name>
  </mads:authority>
  <mads:variant type="other" lang="grc">
    <mads:name type="personal">
      <mads:namePart>Καλλικράτης</mads:namePart>
    </mads:name>
  </mads:variant>
  <mads:variant>
    <mads:name>
      <mads:namePart>Kallikrates</mads:namePart>
    </mads:name>
  </mads:variant>
  <mads:note type="history">CAF 2,416; FCG 1,418</mads:note>
  <mads:fieldOfActivity>Comic Poet</mads:fieldOfActivity>
  <mads:url displayLabel="Wikipedia"/>
  <mads:url displayLabel="VIAF">https://viaf.org/viaf/29920439/</mads:url>
  <mads:url displayLabel="Smith's Dictionary"
    >http://www.perseus.tufts.edu/hopper/text?doc=Perseus:text:1999.04.0104:entry=callicrates-bio-5</mads:url>
  <mads:identifier type="citeurn">urn:cite:perseus:author.304.1</mads:identifier>
  <mads:identifier type="tlg">1783</mads:identifier>
  <mads:extension>
    <mads:description>List of related work identifiers</mads:description>
    <mads:identifier type="tlg">1783.001</mads:identifier>
  </mads:extension>
  <mads:recordInfo>
    <mads:recordContentSource authority="marcorg">0000</mads:recordContentSource>
    <mads:recordCreationDate encoding="marc">930416</mads:recordCreationDate>
    <mads:recordChangeDate encoding="iso8601">19960808164013.0</mads:recordChangeDate>
    <mads:recordIdentifier source="DNB">DNB|102383723</mads:recordIdentifier>
    <mads:languageOfCataloging>
      <mads:languageTerm authority="iso639-2b" type="code">ger</mads:languageTerm>
    </mads:languageOfCataloging>
  </mads:recordInfo>
</mads:mads>
