<?xml version="1.0" encoding="UTF-8"?>
<mads xmlns="http://www.loc.gov/mads/v2"
  xmlns:xsi="http://www.w3.org/2001/XMLSchema-instance"
  xsi:schemaLocation="http://www.loc.gov/mads/v2 http://www.loc.gov/standards/mads/mads.xsd">
    <authority>
      <name type="personal" authority="viaf" authorityURI="http://viaf.org/viaf/" valueURI="http://viaf.org/viaf/27035216">
        <namePart>Hermogenes</namePart>
        <namePart type="date">active 2nd century</namePart>
      </name>
    </authority>
    <variant type="other" lang="grc">
      <name type="personal">
        <namePart>Ερμογένης</namePart>
        <namePart type="termsOfAddress">ο Ταρσεύς</namePart>
      </name>
    </variant>   
    <variant type="other" lang="lat">
      <name type="personal">
        <namePart>Hermogenes</namePart>
        <namePart type="termsOfAddress">Tarsensis</namePart>
        <namePart type="date">160-225</namePart>
      </name>
    </variant>
    <variant type="other" lang="fre">
      <name type="personal">
        <namePart>Hermogène</namePart>
        <namePart type="termsOfAddress">de Tarse</namePart>
      </name>
    </variant>
    <variant type="other" lang="ita">
      <name type="personal">
        <namePart>Ermogene</namePart>
        <namePart type="termsOfAddress">di Tarso</namePart>
      </name>
    </variant>
    <variant type="other" lang="">
      <name type="personal">
        <namePart>Ermogenês</namePart>
      </name>
    </variant>
    <variant type="other" lang="ger">
      <name type="personal">
        <namePart>Hermogenes</namePart>
        <namePart type="termsOfAddress">von Tarsos</namePart>
      </name>
    </variant>
    <variant type="other" lang="lat"> 
      <name type="personal">
        <namePart>Hermogenes</namePart>
        <namePart type="termsOfAddress">Grammaticus</namePart>
      </name>
    </variant>
    <variant type="other" lang="lat">
      <name type="personal">
        <namePart>Hermogenes</namePart>
        <namePart type="termsOfAddress">Rhetor</namePart>
      </name>
    </variant>
    <variant type="other" lang="eng">
      <name type="personal">
        <namePart>Hermogenes</namePart>
        <namePart type="termsOfAddress">of Tarsus</namePart>
        <namePart type="date">active 2nd century</namePart>
      </name>
    </variant>
    <variant type="other" lang="fre">
      <name type="personal">
        <namePart>Hermogène</namePart>
        <namePart type="termsOfAddress">le Rhéteur</namePart>
      </name>
    </variant>
    <variant type="other">
      <name type="personal">
        <namePart>Pseudo-Ermogene</namePart>
      </name>
    </variant>
    <variant type="other">
      <name type="personal">
        <namePart>Pseudo-Hermogenes</namePart>
      </name>
    </variant>
    <variant type="other">
      <name type="personal">
        <namePart>Pseudo-Hermogène</namePart>
        <namePart type="date">160-225</namePart>
      </name>
    </variant>
    <variant type="other">
      <name type="personal">
        <namePart>Tarszoszi Hermogenész</namePart>
      </name>
    </variant>
    <variant type="other">
      <name type="personal">
        <namePart>Гермоген Тарсский</namePart>
      </name>
    </variant>
    <variant type="other">
      <name type="personal">
        <namePart>Հերմոգենես Տարսոնցի</namePart>
      </name>
    </variant>
  <identifier type="citeurn">urn:cite:perseus:author.2315.1</identifier>
    <note type="source">Smith's Dictionary: "Hermogenes, 6, One of the most celebrated Greek rhetoricians.....</note>
    <fieldOfActivity>Rhetorician</fieldOfActivity>
    <fieldOfActivity>Grammarian</fieldOfActivity>
    <url displayLabel="VIAF">http://viaf.org/viaf/27035216</url>
    <url displayLabel="Smith's Dictionary">http://www.perseus.tufts.edu/hopper/text?doc=Perseus:text:1999.04.0104:entry=hermogenes-bio-6</url>
    <url displayLabel="Wikipedia">https://en.wikipedia.org/wiki/Hermogenes_of_Tarsus</url>
    <identifier type="uri">http://viaf.org/viaf/27035216</identifier>
    <identifier type="tlg">0592</identifier>
    <extension>
      <description>List of related work identifiers</description>
      <identifier type="tlg">0592.001</identifier>
      <identifier type="tlg">0592.002</identifier>
      <identifier type="tlg">0592.003</identifier>
      <identifier type="tlg">0592.004</identifier>
      <identifier type="tlg">0592.005</identifier>
      <identifier type="tlg">0592.006</identifier>
    </extension>    
  </mads>
