<?xml version="1.0" encoding="UTF-8"?>
<mods xmlns="http://www.loc.gov/mods/v3">
  <titleInfo>
    <title>Vergilii Vita Donatiana</title>
  </titleInfo>
  <name authority="viaf" type="personal" authorityURI="http://viaf.org/viaf/" valueURI="http://viaf.org/viaf/59888289/">
    <namePart>Donatus, Tiberius Claudius</namePart>
    <role>
      <roleTerm authority="marcrelator" type="text">creator</roleTerm>
    </role>
  </name>
  <name authority="viaf" type="personal" authorityURI="http://viaf.org/viaf/" valueURI="http://viaf.org/viaf/56994658">
    <namePart>Brummer, Jakob</namePart>
    <namePart type="date">1884-</namePart>
    <role>
      <roleTerm authority="marcrelator" type="text">editor</roleTerm>
    </role>
  </name>
  <language objectPart="text">
    <languageTerm authority="iso639-2b" type="code">lat</languageTerm>
  </language>
  <identifier type="stoa author-text">stoa0110a-stoa002</identifier>
  <identifier type="ctsurn">urn:cts:latinLit:stoa0110a.stoa002.opp-lat1</identifier>
  <part>
    <extent unit="pages">
      <start>1</start>
      <end>19</end>
    </extent>
  </part>
  <location>
    <url displayLabel="SLUB">http://digital.slub-dresden.de/werkansicht/dlf/110503/9/</url>
  </location>
  <relatedItem type="host">
    <!-- Still to do-create authors and IDS -->
    <titleInfo>
      <title>Vitae Vergilianae</title>
    </titleInfo>
    <name authority="viaf" type="personal" authorityURI="http://viaf.org/viaf/" valueURI="http://viaf.org/viaf/56994658">
      <namePart>Brummer, Jakob</namePart>
      <namePart type="date">1884-</namePart>
      <role>
        <roleTerm authority="marcrelator" type="text">editor</roleTerm>
      </role>
    </name>
    <typeOfResource>text</typeOfResource>
    <originInfo>
      <place>
        <placeTerm type="code" authority="marccountry">gw</placeTerm>
      </place>
      <place>
        <placeTerm type="text">Lipsiae</placeTerm>
      </place>
      <publisher>Teubner</publisher>
      <dateIssued>1933</dateIssued>
      <issuance>monographic</issuance>
    </originInfo>
    <language objectPart="text">
      <languageTerm authority="iso639-2b" type="code">lat</languageTerm>
    </language>
    <physicalDescription>
      <form authority="marcform">print</form>
      <extent>xxi, 74 p.</extent>
      <digitalOrigin>digitized other analog</digitalOrigin>
    </physicalDescription>
    <identifier type="oclc">894755416</identifier>
    <location>
      <url displayLabel="WorldCat">http://www.worldcat.org/oclc/894755416</url>
    </location>
    <location>
      <url displayLabel="SLUB">http://digital.slub-dresden.de/id415881102</url>
    </location>
    <recordInfo>
      <recordContentSource authority="marcorg"/>
      <recordCreationDate encoding="marc"/>
      <recordChangeDate encoding="iso8601"/>
      <recordIdentifier/>
    </recordInfo>
  </relatedItem>
</mods>
