<?xml version="1.0" encoding="UTF-8"?>
<mods:mods xmlns:mods="http://www.loc.gov/mods/v3">
  <mods:titleInfo>
    <mods:title>Ammonius sive De mundi opificio disputatio</mods:title>
  </mods:titleInfo>
  <mods:name authority="naf" authorityURI="http://id.loc.gov/authorities/names/" type="personal" valueURI="http://id.loc.gov/authorities/names/n79083928">
    <mods:namePart>Zacharias,</mods:namePart>
    <mods:namePart type="termsOfAddress">Bishop of Mytilene</mods:namePart>
    <mods:role>
      <mods:roleTerm authority="marcrelator" type="text">creator</mods:roleTerm>
    </mods:role>
  </mods:name>
  <mods:name authority="naf" authorityURI="http://id.loc.gov/authorities/names/" type="personal" valueURI="http://id.loc.gov/authorities/names/n87923908">
    <mods:namePart>Boissonade, Jean François,</mods:namePart>
    <mods:namePart type="date">1774-1857</mods:namePart>
    <mods:role>
      <mods:roleTerm authority="marcrelator" type="text">editor</mods:roleTerm>
    </mods:role>
  </mods:name>
  <mods:language objectPart="text">
    <mods:languageTerm authority="iso639-2b" type="code">grc</mods:languageTerm>
  </mods:language>
  <mods:identifier type="tlg">2831.001</mods:identifier>
  <mods:identifier type="ctsurn">urn:cts:greekLit:tlg2831.tlg001.opp-grc1</mods:identifier>
  <mods:part>
    <mods:extent unit="pages">
      <mods:start>79</mods:start>
      <mods:end>152</mods:end>
    </mods:extent>
  </mods:part>
  <mods:location displayLabel="GoogleBooks">
    <mods:url>http://books.google.com/books?id=uN4DAAAAQAAJ&amp;pg=PA79</mods:url>
  </mods:location>
  <mods:location>
    <mods:url displayLabel="HathiTrust">http://hdl.handle.net/2027/hvd.32044055053094?urlappend=%3Bseq=117</mods:url>
  </mods:location>
  <mods:relatedItem type="host">
    <mods:titleInfo>
      <mods:title>De immortalitate animae et mundi consummatione</mods:title>
    </mods:titleInfo>
    <mods:name xmlns:ns2="http://www.w3.org/1999/xlink" authority="dnb" type="personal" ns2:href="http://viaf.org/processed/DNB|118647148">
      <mods:namePart>Aeneas,</mods:namePart>
      <mods:namePart type="termsOfAddress">Gazaeus,</mods:namePart>
      <mods:namePart type="date">430-486</mods:namePart>
      <mods:role>
        <mods:roleTerm authority="marcrelator" type="text">creator</mods:roleTerm>
      </mods:role>
    </mods:name>
    <mods:name authority="naf" authorityURI="http://id.loc.gov/authorities/names/" type="personal" valueURI="http://id.loc.gov/authorities/names/n79083928">
      <mods:namePart>Zacharias,</mods:namePart>
      <mods:namePart type="termsOfAddress">Bishop of Mytilene</mods:namePart>
      <mods:role>
        <mods:roleTerm authority="marcrelator" type="text">creator</mods:roleTerm>
      </mods:role>
    </mods:name>
    <mods:name authority="naf" authorityURI="http://id.loc.gov/authorities/names/" type="personal" valueURI="http://id.loc.gov/authorities/names/n87923908">
      <mods:namePart>Boissonade, Jean François,</mods:namePart>
      <mods:namePart type="date">1774-1857</mods:namePart>
      <mods:role>
        <mods:roleTerm authority="marcrelator" type="text">editor</mods:roleTerm>
      </mods:role>
    </mods:name>
    <mods:name authority="naf" authorityURI="http://id.loc.gov/authorities/names/" type="personal" valueURI="http://id.loc.gov/authorities/names/no91014547">
      <mods:namePart>Du Duc, Fronton,</mods:namePart>
      <mods:namePart type="date">1559-1624</mods:namePart>
      <mods:role>
        <mods:roleTerm authority="marcrelator" type="text">original editor</mods:roleTerm>
      </mods:role>
    </mods:name>
    <mods:name authority="naf" authorityURI="http://id.loc.gov/authorities/names/" type="personal" valueURI="http://id.loc.gov/authorities/names/n85143405">
      <mods:namePart>Tarin, Jean, </mods:namePart>
      <mods:namePart type="date">1586-1666</mods:namePart>
      <mods:role>
        <mods:roleTerm authority="marcrelator" type="text">original editor</mods:roleTerm>
      </mods:role>
    </mods:name>
    <mods:name authority="naf" authorityURI="http://id.loc.gov/authorities/names/" type="personal" valueURI="http://id.loc.gov/authorities/names/nr97026348">
      <mods:namePart>Barth, Caspar Von </mods:namePart>
      <mods:role>
        <mods:roleTerm authority="marcrelator" type="text">original editor</mods:roleTerm>
      </mods:role>
    </mods:name>
    <mods:typeOfResource>text</mods:typeOfResource>
    <mods:originInfo>
      <mods:place>
        <mods:placeTerm type="code" authority="marccountry">fr</mods:placeTerm>
      </mods:place>
      <mods:place>
        <mods:placeTerm type="text">Paris</mods:placeTerm>
      </mods:place>
      <mods:publisher>Mercklein</mods:publisher>
      <mods:dateIssued>1836</mods:dateIssued>
      <mods:edition/>
      <mods:issuance>monographic</mods:issuance>
    </mods:originInfo>
    <mods:language objectPart="preface">
      <mods:languageTerm authority="iso639-2b" type="code">lat</mods:languageTerm>
    </mods:language>
    <mods:language objectPart="text">
      <mods:languageTerm authority="iso639-2b" type="code">grc</mods:languageTerm>
    </mods:language>
    <mods:physicalDescription>
      <mods:form authority="marcform">print</mods:form>
      <mods:extent>XXV, 530 S.</mods:extent>
    </mods:physicalDescription>
    <mods:subject authority="lcsh">
      <mods:topic>Immortality</mods:topic>
    </mods:subject>
    <mods:classification authority="lcc"/>
    <mods:classification authority="ddc"/>
    <mods:identifier type="oclc">165621488</mods:identifier>
    <mods:location>
      <mods:url displayLabel="WorldCat">http://www.worldcat.org/oclc/165621488</mods:url>
    </mods:location>
    <mods:location>
      <mods:url displayLabel="Open Content Alliance"/>
    </mods:location>
    <mods:location>
      <mods:url displayLabel="Open Library"/>
    </mods:location>
    <mods:location>
      <mods:url displayLabel="GoogleBooks">http://books.google.com/books?id=uN4DAAAAQAAJ</mods:url>
    </mods:location>
    <mods:location>
      <mods:url displayLabel="HathiTrust">http://hdl.handle.net/2027/hvd.32044055053094</mods:url>
    </mods:location>
    <mods:recordInfo>
      <mods:recordContentSource authority="marcorg"/>
      <mods:recordCreationDate encoding="marc"/>
      <mods:recordChangeDate encoding="iso8601"/>
      <mods:recordIdentifier/>
    </mods:recordInfo>
  </mods:relatedItem>
</mods:mods>
