<?xml version="1.0"?>
<mads:mads xmlns:xlink="http://www.w3.org/1999/xlink" xmlns:mads="http://www.loc.gov/mads/v2" xmlns:xsi="http://www.w3.org/2001/XMLSchema-instance" version="2.0" xsi:schemaLocation="http://www.loc.gov/mads/v2 http://www.loc.gov/standards/mads/mads.xsd">
  <mads:authority geographicSubdivision="not applicable">
    <mads:name type="personal" authority="naf">
      <mads:namePart>Julius Montanus</mads:namePart>
      <mads:namePart type="date">d. 27</mads:namePart>
    </mads:name>
  </mads:authority>
  <mads:variant type="other">
    <mads:name type="personal">
      <mads:namePart>Iulius Montanus</mads:namePart>
      <mads:namePart type="date">d. 27</mads:namePart>
    </mads:name>
  </mads:variant>
  <mads:variant type="other">
    <mads:name type="personal">
      <mads:namePart>Montanus, Iulius</mads:namePart>
      <mads:namePart type="date">d. 27</mads:namePart>
    </mads:name>
  </mads:variant>
  <mads:variant type="other">
    <mads:name type="personal">
      <mads:namePart>Montanus, Julius</mads:namePart>
      <mads:namePart type="date">d. 27</mads:namePart>
    </mads:name>
  </mads:variant>
  <mads:variant type="other">
    <mads:name type="personal">
      <mads:namePart>Montanus, Votienus</mads:namePart>
      <mads:namePart type="date">d. 27</mads:namePart>
    </mads:name>
  </mads:variant>
  <mads:variant type="other">
    <mads:name type="personal">
      <mads:namePart>Votienus Montanus</mads:namePart>
      <mads:namePart type="date">d. 27</mads:namePart>
    </mads:name>
  </mads:variant>
  <mads:variant type="other">
    <mads:name type="personal">
      <mads:namePart>Julius Montanus, C</mads:namePart>
      <mads:namePart type="date">d. 27</mads:namePart>
    </mads:name>
  </mads:variant>
  <mads:note type="source">His Carmina [CF] 1991: PHI CD ROM #5.3, Latin Canon, bibliographic screen (Iulius Montanus)</mads:note>
  <mads:note type="source">Oxford class. dict., 1st ed.: p. 954 (Votienus Montanus; orator from Narbo; prosecuted for treason under Tiberius; died in exile A.D. 27)</mads:note>
  <mads:note type="source">Pauly-Wissowa: 19. Halbbd., col. 681-682; "Iuliu", #364 ((C.) Iulius Montanus)</mads:note>
  <mads:note type="source">A Dict. of Greek and Roman biography and mythology, 1967: v. 2, p. 1113 (Montanus, Julius)</mads:note>
  <mads:identifier type="lccn">nr 95021875 </mads:identifier>
  <mads:fieldOfActivity>Poet</mads:fieldOfActivity>
  <mads:fieldOfActivity>Latin Poet</mads:fieldOfActivity>
  <mads:note type="source">TLG Canon of Greek Authors and Works, Third Edition,</mads:note>
  <mads:note type="source">Smith's Dictionary of Greek and Roman Biography and Mythology, Vol , 1867, p. 1: </mads:note>
  <mads:note type="source">Brill's New Pauly:  "Montanus, Iulius, Poet of the early Principiate,..."</mads:note>
  <mads:url displayLabel="Wikipedia"/>
  <mads:url displayLabel="Worldcat Identities"/>
  <mads:url displayLabel="Smith's Dictionary"/>
  <mads:url displayLabel="VIAF"/>
  <mads:identifier type="phi">938</mads:identifier>
  <mads:identifier type="citeurn">urn:cite:perseus:author.796.1</mads:identifier>
  <mads:extension>
    <mads:description>List of related work identifiers</mads:description>
    <identifier type="phi">938.1</identifier>
  </mads:extension>
  <mads:recordInfo>
    <mads:recordOrigin>Converted from MARCXML to MADS version 2.0 using MARC21slim2MODS-2-0.xsl (Revision 2.07)</mads:recordOrigin>
    <mads:recordContentSource authority="marcorg">NNC</mads:recordContentSource>
    <mads:recordChangeDate encoding="iso8601">20001104070821.0</mads:recordChangeDate>
    <mads:recordIdentifier source="DLC">nr95021875</mads:recordIdentifier>
    <mads:languageOfCataloging>
      <mads:languageTerm authority="iso639-2b" type="code">eng</mads:languageTerm>
    </mads:languageOfCataloging>
    <mads:descriptionStandard>aacr2</mads:descriptionStandard>
  </mads:recordInfo>
</mads:mads>
