<mads:mads xmlns:xlink="http://www.w3.org/1999/xlink" xmlns:mods="http://www.loc.gov/mods/v3" xmlns:mads="http://www.loc.gov/mads/v2" xmlns:xsi="http://www.w3.org/2001/XMLSchema-instance" version="2.0" xsi:schemaLocation="http://www.loc.gov/mads/ http://www.loc.gov/standards/mads/mads.xsd http://www.loc.gov/mods/v3 http://www.loc.gov/standards/mods/v3/mods-3-2.xsd"><mads:authority><mads:name type="personal" authority="naf"><mads:namePart>Cleonides</mads:namePart><mads:namePart type="date">2nd cent</mads:namePart></mads:name></mads:authority><mads:variant type="other" lang="grc"><mads:name type="personal" authority="Brill"><mads:namePart>Κλεονείδης</mads:namePart></mads:name></mads:variant><mads:variant type="other" lang="fre"><mads:name type="personal" authority="viaf"><mads:namePart>Cléonide‏</mads:namePart></mads:name></mads:variant><mads:variant type="other" lang="ita"><mads:name type="personal" authority="viaf"><mads:namePart>Cleonide</mads:namePart></mads:name></mads:variant><mads:variant type="other" lang=""><mads:name type="personal" authority=""><mads:namePart>Kleōneídēs‏</mads:namePart><mads:namePart type="termsOfAddress"/></mads:name></mads:variant><mads:variant type="other" lang=""><mads:name type="personal" authority=""><mads:namePart>Kleōnídēs‏</mads:namePart><mads:namePart type="termsOfAddress"/></mads:name></mads:variant><mads:variant type="other" lang=""><mads:name type="personal" authority=""><mads:namePart>Kleōnídīs‏</mads:namePart><mads:namePart type="termsOfAddress"/></mads:name></mads:variant><mads:variant type="other"><mads:name type="personal" authority="lsj"><mads:namePart>Cleonides</mads:namePart><mads:namePart type="termsOfAddress">Musicus</mads:namePart></mads:name></mads:variant><mads:variant type="abbreviation"><mads:name type="personal" authority="lsj"><mads:namePart>Cleonid.</mads:namePart></mads:name></mads:variant><mads:note type="source">Hoc in uolumine haec opera continentur Cleonidae Harmonicum introductorium, 1497</mads:note><mads:note type="source">New Grove dict. of music (Cleonides; fl. 2nd cent. A.D.; author of Eisagōgē 
      harmonikē, formerly attributed to Euclid)</mads:note><mads:identifier type="lccn">nr 97015947</mads:identifier><mads:fieldOfActivity>Musician</mads:fieldOfActivity><mads:fieldOfActivity>Musical Author</mads:fieldOfActivity><mads:note type="source">TLG Canon of Greek Authors and Works, Third Edition, pg. 102</mads:note><mads:note type="source">Smith's Dictionary of Greek and Roman Biography and Mythology, Vol , 1867, p. 1: </mads:note><mads:note type="source">Brill's New Pauly:  "Cleonides, presumably the author of an Εἰσαγωγὴ ἁρμονική/Eisagōgḕ harmonikḗ (‘Introduction to Harmonics) in
      Aristoxenian tradition ( Aristoxenus ), perhaps 2nd cent. AD..." Najock, Dietmar (Berlin). "Cleonides." Brill's New Pauly. Antiquity volumes edited by: Hubert Cancik and ; Helmuth Schneider . Brill, 2011. Brill Online. Tufts University Library. 03 March 2011</mads:note><mads:url displayLabel="Wikipedia">http://en.wikipedia.org/wiki/Cleonides</mads:url><mads:url displayLabel="Worldcat Identities">http://worldcat.org/identities/np-cleonides</mads:url><mads:url displayLabel="Smith's Dictionary"/><mads:identifier type="tlg">0361</mads:identifier><mads:extension><mads:description>List of related work identifiers</mads:description><identifier type="tlg">0361.001</identifier></mads:extension><mads:recordInfo><mads:recordContentSource authority="marcorg">CSt</mads:recordContentSource><mads:recordCreationDate encoding="marc">970430</mads:recordCreationDate><mads:recordChangeDate encoding="iso8601">19970516051118.4</mads:recordChangeDate><mads:recordIdentifier>oca04343128 </mads:recordIdentifier></mads:recordInfo></mads:mads>