<?xml version="1.0" encoding="UTF-8"?>
<mods:mods xmlns:mods="http://www.loc.gov/mods/v3"
           xmlns:xsi="http://www.w3.org/2001/XMLSchema-instance"
           xmlns:atom="http://www.w3.org/2005/Atom"
           xsi:schemaLocation="http://www.loc.gov/mods/v3 http://www.loc.gov/standards/mods/v3/mods-3-4.xsd">
                <mods:titleInfo xml:lang="en" type="uniform">
                    <mods:title>Epistula</mods:title>
                </mods:titleInfo>
                <mods:titleInfo xmlns="http://www.loc.gov/mods/v3">
                    <mods:title>Epistulae</mods:title>
                    <mods:partNumber>Book VII-X</mods:partNumber>
                </mods:titleInfo>
                <mods:identifier type="stoa author-text">stoa0261-stoa002</mods:identifier>
                <mods:identifier>Perseus:text:2008.01.0550</mods:identifier>
                <mods:identifier type="ctsurn">urn:cts:latinLit:stoa0261.stoa002.opp-lat1</mods:identifier>
                <mods:name xmlns="http://www.loc.gov/mods/v3"
              xmlns:ns2="http://www.w3.org/1999/xlink"
              authority="naf"
              type="personal"
              ns2:href="http://errol.oclc.org/laf/n85-175817.html">
                    <mods:namePart>Sidonius Apollinaris</mods:namePart>
                    <mods:namePart type="termsOfAddress">Saint</mods:namePart>
                    <mods:namePart type="date">431 or 2-ca. 487</mods:namePart>
                    <mods:role>
                        <mods:roleTerm authority="marcrelator" type="text">creator</mods:roleTerm>
                    </mods:role>
                </mods:name>
                <mods:name xmlns="http://www.loc.gov/mods/v3"
              authority="naf"
              type="personal"
              authorityURI="http://id.loc.gov/authorities/names/nr2001037462.html">
                    <mods:namePart>Lütjohann, Christian, </mods:namePart>
                    <mods:namePart type="date">1846-1884</mods:namePart>
                    <mods:role>
                        <mods:roleTerm authority="marcrelator" type="text">editor</mods:roleTerm>
                    </mods:role>
                </mods:name>
                <mods:language xmlns="http://www.loc.gov/mods/v3">
                    <mods:languageTerm authority="iso639-2b" type="code">lat</mods:languageTerm>
                </mods:language>
                <mods:location xmlns="http://www.loc.gov/mods/v3">
                    <mods:url displayLabel="Perseus" note="Latin">http://www.perseus.tufts.edu/hopper/text?doc=Perseus:text:2008.01.0550</mods:url>
                </mods:location>
                <mods:relatedItem xmlns="http://www.loc.gov/mods/v3" type="host">
                    <mods:titleInfo>
                        <mods:title>Gai Sollii Apollinaris Sidonii Epistvlae et carmina</mods:title>
                    </mods:titleInfo>
                    <mods:name xmlns:ns2="http://www.w3.org/1999/xlink"
                 authority="naf"
                 type="personal"
                 ns2:href="http://errol.oclc.org/laf/n85-175817.html             ">
                        <mods:namePart>Sidonius Apollinaris</mods:namePart>
                        <mods:namePart type="termsOfAddress">Saint</mods:namePart>
                        <mods:namePart type="date">431 or 2-ca. 487</mods:namePart>
                        <mods:role>
                            <mods:roleTerm authority="marcrelator" type="text">creator</mods:roleTerm>
                        </mods:role>
                    </mods:name>
                    <mods:name authority="naf"
                 type="personal"
                 authorityURI="http://id.loc.gov/authorities/names/nr2001037462.html">
                        <mods:namePart>Lütjohann, Christian, </mods:namePart>
                        <mods:namePart type="date">1846-1884</mods:namePart>
                        <mods:role>
                            <mods:roleTerm authority="marcrelator" type="text">editor</mods:roleTerm>
                        </mods:role>
                    </mods:name>
                    <mods:typeOfResource>text</mods:typeOfResource>
                    <mods:originInfo>
                        <mods:place>
                            <mods:placeTerm type="code" authority="marccountry">gw</mods:placeTerm>
                        </mods:place>
                        <mods:place>
                            <mods:placeTerm type="text">Berolini</mods:placeTerm>
                        </mods:place>
                        <mods:publisher>apvd Weidmannos</mods:publisher>
                        <mods:dateIssued>1887</mods:dateIssued>
                        <mods:issuance>monographic</mods:issuance>
                    </mods:originInfo>
                    <mods:language>
                        <mods:languageTerm type="code" authority="iso639-2b">lat</mods:languageTerm>
                    </mods:language>
                    <mods:physicalDescription>
                        <mods:form authority="marcform">print</mods:form>
                        <mods:extent>lxxvii p., 1 l., 484 p. 30 cm.</mods:extent>
                    </mods:physicalDescription>
                    <mods:subject authority="lcsh">
                        <mods:name type="personal">
                            <mods:namePart type="termsOfAddress">Saint</mods:namePart>
                            <mods:namePart>Sidonius Apollinaris</mods:namePart>
                            <mods:namePart type="date">431 or 2-ca. 487</mods:namePart>
                        </mods:name>
                    </mods:subject>
                    <mods:classification authority="lcc">DD3.M8 A8 vol. 8</mods:classification>
                    <mods:relatedItem type="series">
                        <mods:titleInfo>
                            <mods:title>Monumenta Germaniae historica inde ab anno Christi quingentesimo usque ad annum millesimum et quingentesimum. t. 8</mods:title>
                            <mods:partName>Auctores antiquissimi</mods:partName>
                        </mods:titleInfo>
                    </mods:relatedItem>
                    <mods:identifier type="lccn">ac 35000561</mods:identifier>
                    <mods:identifier type="oclc">258704785</mods:identifier>
                    <mods:location>
                        <mods:url displayLabel="LC Permalink">http://lccn.loc.gov/ac35000561</mods:url>
                    </mods:location>
                    <mods:location>
                        <mods:url displayLabel="WorldCat">http://www.worldcat.org/title/gai-sollii-apollinaris-sidonii-epistulae-et-carmina/oclc/258704785</mods:url>
                    </mods:location>
                    <mods:location>
                        <mods:url displayLabel="Open Content Alliance"/>
                    </mods:location>
                    <mods:location>
                        <mods:url displayLabel="Open Library"/>
                    </mods:location>
                    <mods:location>
                        <mods:url displayLabel="GoogleBooks">http://books.google.com/books?id=W-0JAAAAIAAJ</mods:url>
                    </mods:location>
                </mods:relatedItem>
            </mods:mods>
