<?xml version="1.0"?>
<mads:mads xmlns:xlink="http://www.w3.org/1999/xlink" xmlns:mods="http://www.loc.gov/mods/v3" xmlns:mads="http://www.loc.gov/mads/v2" xmlns:xsi="http://www.w3.org/2001/XMLSchema-instance" xsi:schemaLocation="http://www.loc.gov/mads/ http://www.loc.gov/standards/mads/mads.xsd http://www.loc.gov/mods/v3 http://www.loc.gov/standards/mods/v3/mods-3-2.xsd" version="2.0">
  <mads:authority>
    <mads:name type="personal" authority="naf">
      <mads:namePart>Lysias</mads:namePart>
    </mads:name>
  </mads:authority>
  <mads:variant type="other">
    <mads:name type="personal">
      <mads:namePart>Lusias</mads:namePart>
    </mads:name>
  </mads:variant>
  <mads:variant type="other" lang="grc">
    <mads:name type="personal" authority="Brill">
      <mads:namePart>&#x39B;&#x3C5;&#x3C3;&#x3AF;&#x3B1;&#x3C2;</mads:namePart>
    </mads:name>
  </mads:variant>
  <mads:variant type="other" lang="cat">
    <mads:name type="personal">
      <mads:namePart>L&#xFC;sziasz
            </mads:namePart>
    </mads:name>
  </mads:variant>
  <mads:variant type="other" lang="hun">
    <mads:name type="personal">
      <mads:namePart>L&#xED;sies</mads:namePart>
    </mads:name>
  </mads:variant>
  <mads:variant type="other" lang="ita">
    <mads:name type="personal">
      <mads:namePart>Lisia</mads:namePart>
    </mads:name>
  </mads:variant>
  <mads:variant type="other" lang="jap">
    <mads:name type="personal">
      <mads:namePart>&#x30EA;&#x30E5;&#x30B7;&#x30A2;&#x30B9;</mads:namePart>
    </mads:name>
  </mads:variant>
  <mads:variant type="other" lang="pol">
    <mads:name type="personal">
      <mads:namePart>Lizjasz</mads:namePart>
    </mads:name>
  </mads:variant>
  <mads:variant type="other" lang="spa">
    <mads:name type="personal">
      <mads:namePart>Lisias</mads:namePart>
    </mads:name>
  </mads:variant>
  <mads:variant type="other">
    <mads:name type="personal" authority="lsj">
      <mads:namePart>Lysias</mads:namePart>
      <mads:namePart type="termsOfAddress">Orator</mads:namePart>
    </mads:name>
  </mads:variant>
  <mads:variant type="abbreviation">
    <mads:name type="personal" authority="lsj">
      <mads:namePart>Lys.</mads:namePart>
    </mads:name>
  </mads:variant>
  <mads:note type="source">His Der Ra&#xCC;&#x88;cher seiner Ehre, 1983: t.p. (Lysias) p. 4 of
        cover (ca. 445-ca. 380 B.C.)</mads:note>
  <mads:identifier type="citeurn">urn:cite:perseus:author.864.1</mads:identifier>
  <mads:identifier type="lccn">n 50000909 </mads:identifier>
  <mads:fieldOfActivity>Orator</mads:fieldOfActivity>
  <mads:fieldOfActivity>Attic Orator</mads:fieldOfActivity>
  <mads:fieldOfActivity>Logographer</mads:fieldOfActivity>
  
  
  
  <mads:url displayLabel="Wikipedia">http://en.wikipedia.org/wiki/Lysias</mads:url>
  <mads:url displayLabel="Worldcat Identities">http://worldcat.org/identities/lccn-n50-909</mads:url>
  <mads:url displayLabel="Smith's Dictionary"/>
  <mads:identifier type="tlg">0540</mads:identifier>
  <mads:identifier type="Perseus:abo">Perseus:abo:tlg,0540,</mads:identifier>
  <mads:extension>
    <mads:description>List of related work identifiers</mads:description>
    <identifier type="tlg">0540.001</identifier>
    <identifier type="tlg">0540.002</identifier>
    <identifier type="tlg">0540.003</identifier>
    <identifier type="tlg">0540.004</identifier>
    <identifier type="tlg">0540.005</identifier>
    <identifier type="tlg">0540.006</identifier>
    <identifier type="tlg">0540.007</identifier>
    <identifier type="tlg">0540.008</identifier>
    <identifier type="tlg">0540.009</identifier>
    <identifier type="tlg">0540.010</identifier>
    <identifier type="tlg">0540.011</identifier>
    <identifier type="tlg">0540.012</identifier>
    <identifier type="tlg">0540.013</identifier>
    <identifier type="tlg">0540.014</identifier>
    <identifier type="tlg">0540.015</identifier>
    <identifier type="tlg">0540.016</identifier>
    <identifier type="tlg">0540.017</identifier>
    <identifier type="tlg">0540.018</identifier>
    <identifier type="tlg">0540.019</identifier>
    <identifier type="tlg">0540.020</identifier>
    <identifier type="tlg">0540.021</identifier>
    <identifier type="tlg">0540.022</identifier>
    <identifier type="tlg">0540.023</identifier>
    <identifier type="tlg">0540.024</identifier>
    <identifier type="tlg">0540.025</identifier>
    <identifier type="tlg">0540.026</identifier>
    <identifier type="tlg">0540.027</identifier>
    <identifier type="tlg">0540.028</identifier>
    <identifier type="tlg">0540.029</identifier>
    <identifier type="tlg">0540.030</identifier>
    <identifier type="tlg">0540.031</identifier>
    <identifier type="tlg">0540.032</identifier>
    <identifier type="tlg">0540.033</identifier>
    <identifier type="tlg">0540.034</identifier>
  </mads:extension>
  <mads:recordInfo>
    <mads:recordContentSource authority="marcorg">DLC</mads:recordContentSource>
    <mads:recordCreationDate encoding="marc">800208</mads:recordCreationDate>
    <mads:recordChangeDate encoding="iso8601">20021112110217.0</mads:recordChangeDate>
    <mads:recordIdentifier>oca00036610 </mads:recordIdentifier>
    <mads:languageOfCataloging>
      <mads:languageTerm type="code" authority="iso639-2b">eng</mads:languageTerm>
    </mads:languageOfCataloging>
  </mads:recordInfo>
</mads:mads>
